evalo/__init__.py
evalo/evalo.py
evalo/reify.py
evalo/solve.py
evalo/utils.py
evalo-0.2.0.dist-info/LICENSE
evalo-0.2.0.dist-info/METADATA
evalo-0.2.0.dist-info/WHEEL
evalo-0.2.0.dist-info/top_level.txt
evalo-0.2.0.dist-info/RECORD
