Metadata-Version: 2.1
Name: evalo
Version: 0.2.0
Summary: Reverse evaluate values to Python code using constraint solving
Home-page: https://github.com/AlexanderGrooff/python-code-synthesis
Author: Alexander Grooff
Author-email: alexandergrooff@gmail.com
License: UNKNOWN
Platform: UNKNOWN
Classifier: Programming Language :: Python :: 3
Classifier: License :: OSI Approved :: MIT License
Classifier: Operating System :: OS Independent
Requires-Python: >=3.6
